adminfinder/__init__.py
adminfinder/app.py
adminfinder-1.0.3.dist-info/LICENSE
adminfinder-1.0.3.dist-info/LICENSE.txt
adminfinder-1.0.3.dist-info/METADATA
adminfinder-1.0.3.dist-info/WHEEL
adminfinder-1.0.3.dist-info/entry_points.txt
adminfinder-1.0.3.dist-info/top_level.txt
adminfinder-1.0.3.dist-info/RECORD
